;-------------------------------------------------------------------------------
; File generated by dirtyJOE v1.7 (c529) (x64)
; Copyright © 2008-2014 ReWolf
; http://dirty-joe.com
; joe@dirty-joe.com
;-------------------------------------------------------------------------------

public void <init>()
00000000: 	aload_0
00000001: 	invokespecial       void java.lang.Object.<init>()
00000004: 	return
;-------------------------------------------------------------------------------

public static void main(java.lang.String[])
00000000: 	iconst_0
00000001: 	istore_1
00000002: 	iload_1
00000003: 	sipush              1000
00000006: 	if_icmpge           pos.00000017
00000009: 	getstatic           java.io.PrintStream java.lang.System.out
0000000C: 	ldc                 "??"
0000000E: 	invokevirtual       void java.io.PrintStream.print(java.lang.String)
00000011: 	iinc                local.01, 1
00000014: 	goto                pos.00000002
;-------------------------------------------------------------------------------
00000017: 	return
;-------------------------------------------------------------------------------

